{
  "executedAt": "2025-11-04T19:01:25.153Z",
  "restaurant": "Prince of Wales Pub (Bromham)",
  "date": "2025-11-10",
  "config": {
    "TARGET_RESTAURANT_SLUG": "prince-of-wales-pub-bromham",
    "TARGET_DATE": "2025-11-10",
    "MAX_CONCURRENT_BOOKINGS": 15,
    "SINGLE_ATTEMPT_ONLY": true,
    "HOLD_TTL_SECONDS": 180,
    "MINIMAL_CONSOLE_OUTPUT": false,
    "FORCE_REASSIGN_ALL": false
  },
  "totalBookings": 100,
  "pendingProcessed": 100,
  "successful": 0,
  "failed": 100,
  "successRate": 0,
  "totalDurationSeconds": 265.52,
  "avgProcessingMs": 26111,
  "results": [
    {
      "id": "5f0b5152",
      "time": "12:00:00",
      "party": 4,
      "success": false,
      "reason": "No suitable tables available",
      "tablesAssigned": [],
      "durationMs": 36665
    },
    {
      "id": "3c3c3c0a",
      "time": "12:00:00",
      "party": 2,
      "success": false,
      "reason": "No suitable tables available",
      "tablesAssigned": [],
      "durationMs": 32799
    },
    {
      "id": "12e7954b",
      "time": "12:00:00",
      "party": 2,
      "success": false,
      "reason": "No suitable tables available",
      "tablesAssigned": [],
      "durationMs": 32558
    },
    {
      "id": "ecd352fa",
      "time": "12:00:00",
      "party": 4,
      "success": false,
      "reason": "No suitable tables available",
      "tablesAssigned": [],
      "durationMs": 36732
    },
    {
      "id": "1c631779",
      "time": "12:15:00",
      "party": 3,
      "success": false,
      "reason": "No suitable tables available",
      "tablesAssigned": [],
      "durationMs": 23191
    },
    {
      "id": "39a4b143",
      "time": "12:30:00",
      "party": 3,
      "success": false,
      "reason": "No suitable tables available",
      "tablesAssigned": [],
      "durationMs": 21579
    },
    {
      "id": "95cf213c",
      "time": "12:45:00",
      "party": 2,
      "success": false,
      "reason": "No suitable tables available",
      "tablesAssigned": [],
      "durationMs": 32056
    },
    {
      "id": "dd755ca1",
      "time": "12:45:00",
      "party": 4,
      "success": false,
      "reason": "No suitable tables available",
      "tablesAssigned": [],
      "durationMs": 35287
    },
    {
      "id": "a07fbaa8",
      "time": "12:45:00",
      "party": 4,
      "success": false,
      "reason": "No suitable tables available",
      "tablesAssigned": [],
      "durationMs": 36519
    },
    {
      "id": "588e56a5",
      "time": "12:45:00",
      "party": 5,
      "success": false,
      "reason": "No suitable tables available",
      "tablesAssigned": [],
      "durationMs": 17935
    },
    {
      "id": "a34d30c5",
      "time": "12:45:00",
      "party": 3,
      "success": false,
      "reason": "No suitable tables available",
      "tablesAssigned": [],
      "durationMs": 24023
    },
    {
      "id": "615ac665",
      "time": "13:00:00",
      "party": 3,
      "success": false,
      "reason": "No suitable tables available",
      "tablesAssigned": [],
      "durationMs": 23046
    },
    {
      "id": "5aa9f614",
      "time": "13:00:00",
      "party": 2,
      "success": false,
      "reason": "No suitable tables available",
      "tablesAssigned": [],
      "durationMs": 32583
    },
    {
      "id": "09c13452",
      "time": "13:00:00",
      "party": 6,
      "success": false,
      "reason": "No suitable tables available",
      "tablesAssigned": [],
      "durationMs": 23807
    },
    {
      "id": "e013b0d4",
      "time": "13:00:00",
      "party": 8,
      "success": false,
      "reason": "No suitable tables available",
      "tablesAssigned": [],
      "durationMs": 15030
    },
    {
      "id": "023e92e8",
      "time": "13:00:00",
      "party": 4,
      "success": false,
      "reason": "No suitable tables available",
      "tablesAssigned": [],
      "durationMs": 35725
    },
    {
      "id": "d2f21165",
      "time": "13:15:00",
      "party": 4,
      "success": false,
      "reason": "No suitable tables available",
      "tablesAssigned": [],
      "durationMs": 37109
    },
    {
      "id": "0de56396",
      "time": "13:15:00",
      "party": 2,
      "success": false,
      "reason": "No suitable tables available",
      "tablesAssigned": [],
      "durationMs": 31415
    },
    {
      "id": "433e4a88",
      "time": "13:15:00",
      "party": 2,
      "success": false,
      "reason": "No suitable tables available",
      "tablesAssigned": [],
      "durationMs": 32574
    },
    {
      "id": "990c91a1",
      "time": "13:30:00",
      "party": 5,
      "success": false,
      "reason": "No suitable tables available",
      "tablesAssigned": [],
      "durationMs": 14900
    },
    {
      "id": "3bf97a6b",
      "time": "13:30:00",
      "party": 4,
      "success": false,
      "reason": "No suitable tables available",
      "tablesAssigned": [],
      "durationMs": 37171
    },
    {
      "id": "8935d539",
      "time": "13:30:00",
      "party": 2,
      "success": false,
      "reason": "No suitable tables available",
      "tablesAssigned": [],
      "durationMs": 33304
    },
    {
      "id": "4db5dbef",
      "time": "13:30:00",
      "party": 4,
      "success": false,
      "reason": "No suitable tables available",
      "tablesAssigned": [],
      "durationMs": 37183
    },
    {
      "id": "279cff32",
      "time": "13:30:00",
      "party": 4,
      "success": false,
      "reason": "No suitable tables available",
      "tablesAssigned": [],
      "durationMs": 37294
    },
    {
      "id": "420974ab",
      "time": "13:30:00",
      "party": 3,
      "success": false,
      "reason": "No suitable tables available",
      "tablesAssigned": [],
      "durationMs": 22129
    },
    {
      "id": "a06961d6",
      "time": "13:30:00",
      "party": 6,
      "success": false,
      "reason": "No suitable tables available",
      "tablesAssigned": [],
      "durationMs": 22703
    },
    {
      "id": "a35a771e",
      "time": "15:00:00",
      "party": 5,
      "success": false,
      "reason": "Reservation would overrun lunch service (end 15:00).",
      "tablesAssigned": [],
      "durationMs": 282
    },
    {
      "id": "585a4ff0",
      "time": "15:00:00",
      "party": 3,
      "success": false,
      "reason": "Reservation would overrun lunch service (end 15:00).",
      "tablesAssigned": [],
      "durationMs": 273
    },
    {
      "id": "4ac68970",
      "time": "15:00:00",
      "party": 4,
      "success": false,
      "reason": "Reservation would overrun lunch service (end 15:00).",
      "tablesAssigned": [],
      "durationMs": 255
    },
    {
      "id": "bd180534",
      "time": "15:15:00",
      "party": 8,
      "success": false,
      "reason": "Reservation would overrun lunch service (end 15:00).",
      "tablesAssigned": [],
      "durationMs": 254
    },
    {
      "id": "5acb5a4b",
      "time": "15:15:00",
      "party": 5,
      "success": false,
      "reason": "Reservation would overrun lunch service (end 15:00).",
      "tablesAssigned": [],
      "durationMs": 275
    },
    {
      "id": "6eba3858",
      "time": "15:15:00",
      "party": 2,
      "success": false,
      "reason": "Reservation would overrun lunch service (end 15:00).",
      "tablesAssigned": [],
      "durationMs": 152
    },
    {
      "id": "3a759807",
      "time": "15:15:00",
      "party": 2,
      "success": false,
      "reason": "Reservation would overrun lunch service (end 15:00).",
      "tablesAssigned": [],
      "durationMs": 125
    },
    {
      "id": "8c6164c9",
      "time": "15:15:00",
      "party": 4,
      "success": false,
      "reason": "Reservation would overrun lunch service (end 15:00).",
      "tablesAssigned": [],
      "durationMs": 171
    },
    {
      "id": "968f548b",
      "time": "15:30:00",
      "party": 4,
      "success": false,
      "reason": "Reservation would overrun lunch service (end 15:00).",
      "tablesAssigned": [],
      "durationMs": 125
    },
    {
      "id": "3f1e03c4",
      "time": "15:30:00",
      "party": 4,
      "success": false,
      "reason": "Reservation would overrun lunch service (end 15:00).",
      "tablesAssigned": [],
      "durationMs": 170
    },
    {
      "id": "73b8c4dc",
      "time": "15:45:00",
      "party": 5,
      "success": false,
      "reason": "Reservation would overrun lunch service (end 15:00).",
      "tablesAssigned": [],
      "durationMs": 151
    },
    {
      "id": "c8df950b",
      "time": "15:45:00",
      "party": 4,
      "success": false,
      "reason": "Reservation would overrun lunch service (end 15:00).",
      "tablesAssigned": [],
      "durationMs": 172
    },
    {
      "id": "879c15d3",
      "time": "16:00:00",
      "party": 2,
      "success": false,
      "reason": "Reservation would overrun lunch service (end 15:00).",
      "tablesAssigned": [],
      "durationMs": 170
    },
    {
      "id": "51e34017",
      "time": "16:00:00",
      "party": 4,
      "success": false,
      "reason": "Reservation would overrun lunch service (end 15:00).",
      "tablesAssigned": [],
      "durationMs": 269
    },
    {
      "id": "e833e123",
      "time": "17:15:00",
      "party": 4,
      "success": false,
      "reason": "No suitable tables available",
      "tablesAssigned": [],
      "durationMs": 38637
    },
    {
      "id": "55ca0209",
      "time": "17:15:00",
      "party": 2,
      "success": false,
      "reason": "No suitable tables available",
      "tablesAssigned": [],
      "durationMs": 35813
    },
    {
      "id": "0783c286",
      "time": "17:15:00",
      "party": 4,
      "success": false,
      "reason": "No suitable tables available",
      "tablesAssigned": [],
      "durationMs": 39312
    },
    {
      "id": "979fb045",
      "time": "17:30:00",
      "party": 4,
      "success": false,
      "reason": "No suitable tables available",
      "tablesAssigned": [],
      "durationMs": 38242
    },
    {
      "id": "efbabfd6",
      "time": "17:30:00",
      "party": 6,
      "success": false,
      "reason": "No suitable tables available",
      "tablesAssigned": [],
      "durationMs": 25735
    },
    {
      "id": "275ac1a0",
      "time": "17:30:00",
      "party": 4,
      "success": false,
      "reason": "No suitable tables available",
      "tablesAssigned": [],
      "durationMs": 36666
    },
    {
      "id": "22e622d4",
      "time": "17:30:00",
      "party": 4,
      "success": false,
      "reason": "No suitable tables available",
      "tablesAssigned": [],
      "durationMs": 36706
    },
    {
      "id": "d0e1fa52",
      "time": "17:30:00",
      "party": 4,
      "success": false,
      "reason": "No suitable tables available",
      "tablesAssigned": [],
      "durationMs": 35139
    },
    {
      "id": "f70b65b3",
      "time": "17:30:00",
      "party": 4,
      "success": false,
      "reason": "No suitable tables available",
      "tablesAssigned": [],
      "durationMs": 36440
    },
    {
      "id": "091a15cb",
      "time": "17:30:00",
      "party": 6,
      "success": false,
      "reason": "No suitable tables available",
      "tablesAssigned": [],
      "durationMs": 23497
    },
    {
      "id": "73843e79",
      "time": "17:30:00",
      "party": 6,
      "success": false,
      "reason": "No suitable tables available",
      "tablesAssigned": [],
      "durationMs": 24836
    },
    {
      "id": "1843322b",
      "time": "17:45:00",
      "party": 4,
      "success": false,
      "reason": "No suitable tables available",
      "tablesAssigned": [],
      "durationMs": 36566
    },
    {
      "id": "f92adccf",
      "time": "17:45:00",
      "party": 2,
      "success": false,
      "reason": "No suitable tables available",
      "tablesAssigned": [],
      "durationMs": 32256
    },
    {
      "id": "46668a9e",
      "time": "17:45:00",
      "party": 2,
      "success": false,
      "reason": "No suitable tables available",
      "tablesAssigned": [],
      "durationMs": 33286
    },
    {
      "id": "ea28d485",
      "time": "17:45:00",
      "party": 4,
      "success": false,
      "reason": "No suitable tables available",
      "tablesAssigned": [],
      "durationMs": 36194
    },
    {
      "id": "261981ae",
      "time": "17:45:00",
      "party": 2,
      "success": false,
      "reason": "No suitable tables available",
      "tablesAssigned": [],
      "durationMs": 32588
    },
    {
      "id": "27c046b0",
      "time": "17:45:00",
      "party": 4,
      "success": false,
      "reason": "No suitable tables available",
      "tablesAssigned": [],
      "durationMs": 36438
    },
    {
      "id": "dc1e140f",
      "time": "17:45:00",
      "party": 2,
      "success": false,
      "reason": "No suitable tables available",
      "tablesAssigned": [],
      "durationMs": 31366
    },
    {
      "id": "ced7025a",
      "time": "18:00:00",
      "party": 4,
      "success": false,
      "reason": "No suitable tables available",
      "tablesAssigned": [],
      "durationMs": 36179
    },
    {
      "id": "7c9d0bd1",
      "time": "18:00:00",
      "party": 5,
      "success": false,
      "reason": "No suitable tables available",
      "tablesAssigned": [],
      "durationMs": 16171
    },
    {
      "id": "4365a6d8",
      "time": "18:00:00",
      "party": 2,
      "success": false,
      "reason": "No suitable tables available",
      "tablesAssigned": [],
      "durationMs": 32317
    },
    {
      "id": "5119f6e5",
      "time": "18:00:00",
      "party": 4,
      "success": false,
      "reason": "No suitable tables available",
      "tablesAssigned": [],
      "durationMs": 37205
    },
    {
      "id": "660161bb",
      "time": "18:00:00",
      "party": 2,
      "success": false,
      "reason": "No suitable tables available",
      "tablesAssigned": [],
      "durationMs": 31061
    },
    {
      "id": "7ce50dd2",
      "time": "18:00:00",
      "party": 6,
      "success": false,
      "reason": "No suitable tables available",
      "tablesAssigned": [],
      "durationMs": 23572
    },
    {
      "id": "a192a6ad",
      "time": "18:00:00",
      "party": 4,
      "success": false,
      "reason": "No suitable tables available",
      "tablesAssigned": [],
      "durationMs": 37106
    },
    {
      "id": "c9268299",
      "time": "18:00:00",
      "party": 6,
      "success": false,
      "reason": "No suitable tables available",
      "tablesAssigned": [],
      "durationMs": 23486
    },
    {
      "id": "af226cfb",
      "time": "18:15:00",
      "party": 2,
      "success": false,
      "reason": "No suitable tables available",
      "tablesAssigned": [],
      "durationMs": 31602
    },
    {
      "id": "15d06d5b",
      "time": "18:15:00",
      "party": 5,
      "success": false,
      "reason": "No suitable tables available",
      "tablesAssigned": [],
      "durationMs": 16652
    },
    {
      "id": "1bab7e3e",
      "time": "18:30:00",
      "party": 3,
      "success": false,
      "reason": "No suitable tables available",
      "tablesAssigned": [],
      "durationMs": 22021
    },
    {
      "id": "9a292200",
      "time": "18:30:00",
      "party": 3,
      "success": false,
      "reason": "No suitable tables available",
      "tablesAssigned": [],
      "durationMs": 22322
    },
    {
      "id": "c7b57b74",
      "time": "18:45:00",
      "party": 3,
      "success": false,
      "reason": "No suitable tables available",
      "tablesAssigned": [],
      "durationMs": 22420
    },
    {
      "id": "72579253",
      "time": "18:45:00",
      "party": 5,
      "success": false,
      "reason": "No suitable tables available",
      "tablesAssigned": [],
      "durationMs": 15751
    },
    {
      "id": "6555a770",
      "time": "18:45:00",
      "party": 3,
      "success": false,
      "reason": "No suitable tables available",
      "tablesAssigned": [],
      "durationMs": 22036
    },
    {
      "id": "6b07a09b",
      "time": "18:45:00",
      "party": 4,
      "success": false,
      "reason": "No suitable tables available",
      "tablesAssigned": [],
      "durationMs": 35390
    },
    {
      "id": "0a1a3484",
      "time": "19:00:00",
      "party": 6,
      "success": false,
      "reason": "No suitable tables available",
      "tablesAssigned": [],
      "durationMs": 22987
    },
    {
      "id": "f1bf5671",
      "time": "19:00:00",
      "party": 2,
      "success": false,
      "reason": "No suitable tables available",
      "tablesAssigned": [],
      "durationMs": 34302
    },
    {
      "id": "f6ec0151",
      "time": "19:15:00",
      "party": 2,
      "success": false,
      "reason": "No suitable tables available",
      "tablesAssigned": [],
      "durationMs": 36227
    },
    {
      "id": "dcdecc42",
      "time": "19:15:00",
      "party": 3,
      "success": false,
      "reason": "No suitable tables available",
      "tablesAssigned": [],
      "durationMs": 22937
    },
    {
      "id": "898aee2c",
      "time": "19:15:00",
      "party": 2,
      "success": false,
      "reason": "No suitable tables available",
      "tablesAssigned": [],
      "durationMs": 35279
    },
    {
      "id": "c3c665bd",
      "time": "19:15:00",
      "party": 3,
      "success": false,
      "reason": "No suitable tables available",
      "tablesAssigned": [],
      "durationMs": 24400
    },
    {
      "id": "72258e94",
      "time": "19:15:00",
      "party": 2,
      "success": false,
      "reason": "No suitable tables available",
      "tablesAssigned": [],
      "durationMs": 35719
    },
    {
      "id": "6be1d476",
      "time": "19:15:00",
      "party": 4,
      "success": false,
      "reason": "No suitable tables available",
      "tablesAssigned": [],
      "durationMs": 39664
    },
    {
      "id": "a9a7a738",
      "time": "19:15:00",
      "party": 4,
      "success": false,
      "reason": "No suitable tables available",
      "tablesAssigned": [],
      "durationMs": 39710
    },
    {
      "id": "278f2f64",
      "time": "19:30:00",
      "party": 5,
      "success": false,
      "reason": "No suitable tables available",
      "tablesAssigned": [],
      "durationMs": 16834
    },
    {
      "id": "110d5264",
      "time": "19:30:00",
      "party": 5,
      "success": false,
      "reason": "No suitable tables available",
      "tablesAssigned": [],
      "durationMs": 17669
    },
    {
      "id": "356acc85",
      "time": "19:30:00",
      "party": 4,
      "success": false,
      "reason": "No suitable tables available",
      "tablesAssigned": [],
      "durationMs": 38828
    },
    {
      "id": "e7c0e841",
      "time": "19:30:00",
      "party": 4,
      "success": false,
      "reason": "No suitable tables available",
      "tablesAssigned": [],
      "durationMs": 38857
    },
    {
      "id": "a5ecb66d",
      "time": "19:30:00",
      "party": 4,
      "success": false,
      "reason": "No suitable tables available",
      "tablesAssigned": [],
      "durationMs": 39354
    },
    {
      "id": "b2a7070d",
      "time": "19:45:00",
      "party": 2,
      "success": false,
      "reason": "No suitable tables available",
      "tablesAssigned": [],
      "durationMs": 34967
    },
    {
      "id": "22b7dfbe",
      "time": "20:00:00",
      "party": 2,
      "success": false,
      "reason": "No suitable tables available",
      "tablesAssigned": [],
      "durationMs": 36835
    },
    {
      "id": "451942c6",
      "time": "20:00:00",
      "party": 4,
      "success": false,
      "reason": "No suitable tables available",
      "tablesAssigned": [],
      "durationMs": 35326
    },
    {
      "id": "b6316503",
      "time": "20:00:00",
      "party": 6,
      "success": false,
      "reason": "No suitable tables available",
      "tablesAssigned": [],
      "durationMs": 23671
    },
    {
      "id": "4f0ef07a",
      "time": "20:00:00",
      "party": 4,
      "success": false,
      "reason": "No suitable tables available",
      "tablesAssigned": [],
      "durationMs": 36611
    },
    {
      "id": "8afd24af",
      "time": "20:00:00",
      "party": 4,
      "success": false,
      "reason": "No suitable tables available",
      "tablesAssigned": [],
      "durationMs": 37871
    },
    {
      "id": "4ed7b96f",
      "time": "20:00:00",
      "party": 7,
      "success": false,
      "reason": "No suitable tables available",
      "tablesAssigned": [],
      "durationMs": 8623
    },
    {
      "id": "b1338748",
      "time": "20:00:00",
      "party": 4,
      "success": false,
      "reason": "No suitable tables available",
      "tablesAssigned": [],
      "durationMs": 36648
    },
    {
      "id": "1875f649",
      "time": "20:30:00",
      "party": 4,
      "success": false,
      "reason": "No suitable tables available",
      "tablesAssigned": [],
      "durationMs": 36355
    },
    {
      "id": "11fb2f3d",
      "time": "20:30:00",
      "party": 6,
      "success": false,
      "reason": "No suitable tables available",
      "tablesAssigned": [],
      "durationMs": 23375
    },
    {
      "id": "3956e3db",
      "time": "20:30:00",
      "party": 3,
      "success": false,
      "reason": "No suitable tables available",
      "tablesAssigned": [],
      "durationMs": 22366
    },
    {
      "id": "5366dca0",
      "time": "20:30:00",
      "party": 2,
      "success": false,
      "reason": "No suitable tables available",
      "tablesAssigned": [],
      "durationMs": 32529
    }
  ]
}
